open_inference/openapi/__init__.py
open_inference/openapi/client.py
open_inference/openapi/core/__init__.py
open_inference/openapi/core/api_error.py
open_inference/openapi/core/client_wrapper.py
open_inference/openapi/core/datetime_utils.py
open_inference/openapi/core/jsonable_encoder.py
open_inference/openapi/core/remove_none_from_dict.py
open_inference/openapi/errors/__init__.py
open_inference/openapi/errors/bad_request_error.py
open_inference/openapi/errors/internal_server_error.py
open_inference/openapi/errors/not_found_error.py
open_inference/openapi/errors/service_unavailable_error.py
open_inference/openapi/py.typed
open_inference/openapi/types/__init__.py
open_inference/openapi/types/inference_error_response.py
open_inference/openapi/types/inference_request.py
open_inference/openapi/types/inference_response.py
open_inference/openapi/types/metadata_model_error_response.py
open_inference/openapi/types/metadata_model_response.py
open_inference/openapi/types/metadata_server_error_response.py
open_inference/openapi/types/metadata_server_response.py
open_inference/openapi/types/metadata_tensor.py
open_inference/openapi/types/parameters.py
open_inference/openapi/types/request_input.py
open_inference/openapi/types/request_output.py
open_inference/openapi/types/response_output.py
open_inference/openapi/types/tensor_data.py
open_inference_openapi-2.0.0.1.dist-info/METADATA
open_inference_openapi-2.0.0.1.dist-info/WHEEL
open_inference_openapi-2.0.0.1.dist-info/RECORD
