Metadata-Version: 2.1
Name: open-inference-openapi
Version: 2.0.0.1
Summary: Generated OpenAPI client library for the open-inference-protocol
Home-page: https://github.com/open-inference/python-clients
License: Apache-2.0
Keywords: mlserver,kserve,triton,seldon,openvino,amdinfer,pytorch-serve,openapi
Author: Zev Isert
Author-email: zevisert@users.noreply.github.com
Maintainer: Zev Isert
Maintainer-email: zevisert@users.noreply.github.com
Requires-Python: >=3.8,<4.0
Classifier: Intended Audience :: Developers
Classifier: Intended Audience :: System Administrators
Classifier: License :: OSI Approved :: Apache Software License
Classifier: Natural Language :: English
Classifier: Operating System :: OS Independent
Classifier: Programming Language :: Python :: 3
Classifier: Programming Language :: Python :: 3.8
Classifier: Programming Language :: Python :: 3.9
Classifier: Programming Language :: Python :: 3.10
Classifier: Programming Language :: Python :: 3.11
Classifier: Programming Language :: Python :: 3.12
Classifier: Topic :: Software Development :: Libraries
Classifier: Topic :: Software Development :: Libraries :: Python Modules
Classifier: Typing :: Typed
Requires-Dist: httpx
Requires-Dist: pydantic (>1)
Project-URL: Bug Tracker, https://github.com/open-inference/python-clients/issues
Project-URL: Repository, https://github.com/open-inference/python-clients
